[
{
"title": "Fuga in c-moll, fürs Clavier",
"genre": "ワールド",
"wav": "/sessions/eloquent-lucid-lovelace/mnt/伯爵MUSIC/releases/Drey Fugen_ Harmonia Mundi/audio/01 Fuga in c-moll, fürs Clavier.wav",
"inst": true
},
{
"title": "Astroscale",
"genre": "ハウス",
"wav": "/sessions/eloquent-lucid-lovelace/mnt/伯爵MUSIC/releases/Astroscale/audio/01 Astroscale.wav",
"inst": true
},
{
"title": "Calm Down",
"genre": "ハウス",
"wav": "/sessions/eloquent-lucid-lovelace/mnt/伯爵MUSIC/releases/Calm Down/audio/01 Calm Down.wav",
"inst": true
},
{
"title": "Infinite Swipe Hell",
"genre": "ハウス",
"wav": "/sessions/eloquent-lucid-lovelace/mnt/伯爵MUSIC/releases/Infinite Swipe Hell/audio/01 Infinite Swipe Hell.wav",
"inst": true
},
{
"title": "BRANDENBURGER TOR",
"genre": "ニューエイジ",
"wav": "/sessions/eloquent-lucid-lovelace/mnt/伯爵MUSIC/releases/BRANDENBURGER TOR/audio/01 BRANDENBURGER TOR.wav",
"inst": true
},
{
"title": "The Pirate's Roar",
"genre": "ワールド",
"wav": "/sessions/eloquent-lucid-lovelace/mnt/伯爵MUSIC/releases/Are You Pirates？/audio/01 The Pirate's Roar.wav",
"inst": false
},
{
"title": "Captain of the Wildest Sea",
"genre": "ワールド",
"wav": "/sessions/eloquent-lucid-lovelace/mnt/伯爵MUSIC/releases/Are You Pirates？/audio/02 Captain of the Wildest Sea.wav",
"inst": false
},
{
"title": "Tempest of the Crimson Jolly",
"genre": "ワールド",
"wav": "/sessions/eloquent-lucid-lovelace/mnt/伯爵MUSIC/releases/Are You Pirates？/audio/03 Tempest of the Crimson Jolly.wav",
"inst": false
},
{
"title": "KRAKEN DRIVE",
"genre": "ワールド",
"wav": "/sessions/eloquent-lucid-lovelace/mnt/伯爵MUSIC/releases/Are You Pirates？/audio/04 KRAKEN DRIVE.wav",
"inst": false
},
{
"title": "Horn of the Titans",
"genre": "ワールド",
"wav": "/sessions/eloquent-lucid-lovelace/mnt/伯爵MUSIC/releases/Are You Pirates？/audio/05 Horn of the Titans.wav",
"inst": false
},
{
"title": "Aurora Launge",
"genre": "ダウンテンポ",
"wav": "/sessions/eloquent-lucid-lovelace/mnt/伯爵MUSIC/releases/Aurora Launge/audio/01 Aurora Launge.wav",
"inst": true
},
{
"title": "Healing Island",
"genre": "ダウンテンポ",
"wav": "/sessions/eloquent-lucid-lovelace/mnt/伯爵MUSIC/releases/Healing Island/audio/01 Healing Island.wav",
"inst": true
},
{
"title": "Basic Income",
"genre": "ハウス",
"wav": "/sessions/eloquent-lucid-lovelace/mnt/伯爵MUSIC/releases/Basic Income/audio/01 Basic Income.wav",
"inst": false
},
{
"title": "Event Horizon",
"genre": "ハウス",
"wav": "/sessions/eloquent-lucid-lovelace/mnt/伯爵MUSIC/releases/Event Horizon/audio/01 Event Horizon.wav",
"inst": false
},
{
"title": "Love on the move",
"genre": "ハウス",
"wav": "/sessions/eloquent-lucid-lovelace/mnt/伯爵MUSIC/releases/House in the World/audio/01 Love on the move.wav",
"inst": false
},
{
"title": "Let’s Shine Together",
"genre": "エレクトロニカ",
"wav": "/sessions/eloquent-lucid-lovelace/mnt/伯爵MUSIC/releases/Let’s Shine Together/audio/01 Let’s Shine Together.wav",
"inst": true
},
{
"title": "Tears of the Blue Planet",
"genre": "ニューエイジ",
"wav": "/sessions/eloquent-lucid-lovelace/mnt/伯爵MUSIC/releases/Tears of the Blue Planet/audio/01 Tears of the Blue Planet.wav",
"inst": false
},
{
"title": "The Breath of All Things",
"genre": "ニューエイジ",
"wav": "/sessions/eloquent-lucid-lovelace/mnt/伯爵MUSIC/releases/The Breath of All Things/audio/01 The Breath of All Things.wav",
"inst": false
},
{
"title": "M.O.N.D.A.Y / Man Over No Divine Authority Yields",
"genre": "ニューエイジ",
"wav": "/sessions/eloquent-lucid-lovelace/mnt/伯爵MUSIC/releases/WEEK♾️FREAK/audio/05 FUCKIDAY(華金幻想).wav",
"inst": false
},
{
"title": "TUESDAY BURNS SLOW",
"genre": "ニューエイジ",
"wav": "/sessions/eloquent-lucid-lovelace/mnt/伯爵MUSIC/releases/WEEK♾️FREAK/audio/02 TUESDAY BURNS SLOW.wav",
"inst": false
},
{
"title": "WEDLOCK",
"genre": "ニューエイジ",
"wav": "/sessions/eloquent-lucid-lovelace/mnt/伯爵MUSIC/releases/WEEK♾️FREAK/audio/03 WEDLOCK.wav",
"inst": false
},
{
"title": "Deus sive Natura",
"genre": "トランス",
"wav": "/sessions/eloquent-lucid-lovelace/mnt/伯爵MUSIC/releases/Deus sive Natura/audio/01 Deus sive Natura.wav",
"inst": true
},
{
"title": "Floating Sundays",
"genre": "ダウンテンポ",
"wav": "/sessions/eloquent-lucid-lovelace/mnt/伯爵MUSIC/releases/Floating Sundays/audio/01 Floating Sundays.wav",
"inst": false
},
{
"title": "Ginger Mint Tea",
"genre": "ダウンテンポ",
"wav": "/sessions/eloquent-lucid-lovelace/mnt/伯爵MUSIC/releases/Ginger Mint Tea/audio/01 Ginger Mint Tea.wav",
"inst": false
},
{
"title": "Ocean Mirror",
"genre": "ダウンテンポ",
"wav": "/sessions/eloquent-lucid-lovelace/mnt/伯爵MUSIC/releases/Healing Island/audio/02 Ocean Mirror.wav",
"inst": false
},
{
"title": "Silver Path",
"genre": "ダウンテンポ",
"wav": "/sessions/eloquent-lucid-lovelace/mnt/伯爵MUSIC/releases/Healing Island/audio/03 Silver Path.wav",
"inst": false
},
{
"title": "NUY",
"genre": "トランス",
"wav": "/sessions/eloquent-lucid-lovelace/mnt/伯爵MUSIC/releases/NUY/audio/01 NUY.wav",
"inst": true
},
{
"title": "OMNI",
"genre": "トランス",
"wav": "/sessions/eloquent-lucid-lovelace/mnt/伯爵MUSIC/releases/OMNI/audio/01 OMNI.wav",
"inst": true
},
{
"title": "PLAYTHING",
"genre": "トランス",
"wav": "/sessions/eloquent-lucid-lovelace/mnt/伯爵MUSIC/releases/PLAYTHING/audio/01 PLAYTHING.wav",
"inst": true
},
{
"title": "HD 10700",
"genre": "エレクトロニカ",
"wav": "/sessions/eloquent-lucid-lovelace/mnt/伯爵MUSIC/releases/HD 10700/audio/01 HD 10700.wav",
"inst": false
}
]